mseep_polymarket_mcp-0.1.4.dist-info/licenses/LICENSE
polymarket_mcp/__init__.py
polymarket_mcp/server.py
mseep_polymarket_mcp-0.1.4.dist-info/METADATA
mseep_polymarket_mcp-0.1.4.dist-info/WHEEL
mseep_polymarket_mcp-0.1.4.dist-info/entry_points.txt
mseep_polymarket_mcp-0.1.4.dist-info/top_level.txt
mseep_polymarket_mcp-0.1.4.dist-info/RECORD
