Metadata-Version: 2.4
Name: mseep-polymarket_mcp
Version: 0.1.4
Summary: MCP Server for PolyMarket API
Author-email: mseep <support@skydeck.ai>
Requires-Python: >=3.10
License-File: LICENSE
Requires-Dist: mcp>=0.1.0
Requires-Dist: httpx>=0.24.0
Requires-Dist: python-dotenv>=1.0.0
Requires-Dist: py-clob-client
Dynamic: license-file
